web_auth/__init__.py
web_auth/config.py
web_auth/core/__init__.py
web_auth/core/authorization.py
web_auth/core/bridge.py
web_auth/core/context.py
web_auth/core/enum.py
web_auth/core/exception.py
web_auth/core/model.py
web_auth/core/storage.py
web_auth/django/__init__.py
web_auth/django/bridge.py
web_auth/fastapi/__init__.py
web_auth/fastapi/bridge.py
web_auth/flask/__init__.py
web_auth/flask/bridge.py
web_auth_sdk-1.2.0.dist-info/LICENSE
web_auth_sdk-1.2.0.dist-info/METADATA
web_auth_sdk-1.2.0.dist-info/WHEEL
web_auth_sdk-1.2.0.dist-info/RECORD
