Metadata-Version: 2.1
Name: web-auth-sdk
Version: 1.2.0
Summary: authorization SDK used to build protected Web APIs
Home-page: https://github.com/yangaound/web-auth-sdk
License: MIT
Author: Yin Long
Author-email: yangaound@gmail.com
Requires-Python: >=3.8,<3.13
Classifier: Development Status :: 4 - Beta
Classifier: Environment :: Plugins
Classifier: Environment :: Web Environment
Classifier: Framework :: Django
Classifier: Framework :: FastAPI
Classifier: Framework :: Flask
Classifier: Intended Audience :: Developers
Classifier: License :: OSI Approved :: MIT License
Classifier: Operating System :: POSIX
Classifier: Programming Language :: Python
Classifier: Programming Language :: Python :: 3
Classifier: Programming Language :: Python :: 3.8
Classifier: Programming Language :: Python :: 3.9
Classifier: Programming Language :: Python :: 3.10
Classifier: Programming Language :: Python :: 3.11
Classifier: Programming Language :: Python :: 3.12
Classifier: Topic :: Software Development :: Libraries
Requires-Dist: PyJWT (>=2.2.0,<3.0)
Requires-Dist: pydantic (>=1.10.6,<2.0.0)
Project-URL: Repository, https://github.com/yangaound/web-auth-sdk
